ikali.py
ikali-2.0.0.dist-info/licenses/LICENSE
ikali-2.0.0.dist-info/METADATA
ikali-2.0.0.dist-info/WHEEL
ikali-2.0.0.dist-info/entry_points.txt
ikali-2.0.0.dist-info/top_level.txt
ikali-2.0.0.dist-info/RECORD
