Metadata-Version: 2.4
Name: ikali
Version: 2.0.0
Summary: iKali, runs a command when typing ikali into the terminal.
Home-page: https://github.com/HypaTobaYT/ikali
Author: Hypa
Author-email: hypertobayt@gmail.com
Classifier: Programming Language :: Python :: 3
Classifier: License :: OSI Approved :: MIT License
Classifier: Operating System :: POSIX :: Linux
Classifier: Environment :: Console
Requires-Python: >=3.6
License-File: LICENSE
Dynamic: author
Dynamic: author-email
Dynamic: classifier
Dynamic: description
Dynamic: description-content-type
Dynamic: home-page
Dynamic: license-file
Dynamic: requires-python
Dynamic: summary
